data_toolkit/__init__.py
data_toolkit/common_methods.py
data_toolkit/load_raw_data.py
data_toolkit/manual_adjustments.py
data_toolkit/run_data_toolkit.py
data_toolkit/fuels/__init__.py
data_toolkit/fuels/eiaaeo_fuel_price_input_csvs.py
data_toolkit/fuels/eiaaeo_to_fuel_chars_input_csvs.py
data_toolkit/project/__init__.py
data_toolkit/project/common_methods.py
data_toolkit/project/create_monte_carlo_gen_input_csvs_common.py
data_toolkit/project/create_sync_gen_input_csvs_common.py
data_toolkit/project/project_data_filters_common.py
data_toolkit/project/availability/__init__.py
data_toolkit/project/availability/eia860_to_project_availability_input_csvs.py
data_toolkit/project/availability/outages/__init__.py
data_toolkit/project/availability/outages/create_availability_iteration_input_csvs.py
data_toolkit/project/availability/weather_derates/__init__.py
data_toolkit/project/availability/weather_derates/create_monte_carlo_gen_weather_derate_input_csvs.py
data_toolkit/project/availability/weather_derates/create_sync_gen_weather_derate_input_csvs.py
data_toolkit/project/capacity_specified/__init__.py
data_toolkit/project/capacity_specified/eia860_to_project_specified_capacity_input_csvs.py
data_toolkit/project/fixed_cost/__init__.py
data_toolkit/project/fixed_cost/eia860_to_project_fixed_cost_input_csvs.py
data_toolkit/project/load_zones/__init__.py
data_toolkit/project/load_zones/eia860_to_project_load_zone_input_csvs.py
data_toolkit/project/opchar/__init__.py
data_toolkit/project/opchar/eia860_to_project_opchar_input_csvs.py
data_toolkit/project/opchar/fuels/__init__.py
data_toolkit/project/opchar/fuels/eia860_to_project_fuel_input_csvs.py
data_toolkit/project/opchar/heat_rates/__init__.py
data_toolkit/project/opchar/heat_rates/eia860_to_project_heat_rate_input_csvs.py
data_toolkit/project/opchar/hydro/__init__.py
data_toolkit/project/opchar/hydro/create_hydro_iteration_input_csvs.py
data_toolkit/project/opchar/var_profiles/__init__.py
gridpath-2025.10.0.dist-info/licenses/LICENSE.md
gridpath-2025.10.0.dist-info/METADATA
gridpath-2025.10.0.dist-info/WHEEL
gridpath-2025.10.0.dist-info/entry_points.txt
gridpath-2025.10.0.dist-info/top_level.txt
gridpath-2025.10.0.dist-info/RECORD
