Metadata-Version: 2.4
Name: GridPath
Version: 2025.10.0
Summary: A versatile simulation and optimization platform for power-system planning and operations.
Home-page: https://www.gridpath.io
Maintainer: Blue Marble Analytics LLC
Maintainer-email: info@gridpath.io
License: Apache v2
Project-URL: Discussions, https://github.com/blue-marble/gridpath/discussions
Project-URL: Documentation, https://gridpath.readthedocs.io/en/latest/
Project-URL: Issues, https://github.com/blue-marble/gridpath/issues
Project-URL: Source Code, https://github.com/blue-marble/gridpath
Keywords: energy,electricity,power,renewables,planning,operations
Platform: MacOS
Platform: Windows
Platform: Linux
License-File: LICENSE.md
Requires-Dist: Pyomo==6.9.4
Requires-Dist: pandas==2.3.2
Requires-Dist: bokeh==3.8.0
Requires-Dist: pscript==0.8.0
Requires-Dist: networkx==3.4.2; python_version < "3.11"
Requires-Dist: networkx==3.5.0; python_version >= "3.11"
Requires-Dist: PyUtilib==6.0.0
Requires-Dist: dill==0.3.8
Requires-Dist: duckdb==1.4.0
Provides-Extra: doc
Requires-Dist: Sphinx==7.2.6; extra == "doc"
Requires-Dist: sphinx-argparse==0.4.0; extra == "doc"
Requires-Dist: df2img; extra == "doc"
Provides-Extra: all
Requires-Dist: Sphinx==7.2.6; extra == "all"
Requires-Dist: sphinx-argparse==0.4.0; extra == "all"
Requires-Dist: df2img; extra == "all"
Requires-Dist: black; extra == "all"
Requires-Dist: coverage; extra == "all"
Requires-Dist: coveralls; extra == "all"
Requires-Dist: gurobipy; extra == "all"
Requires-Dist: highspy; extra == "all"
Provides-Extra: coverage
Requires-Dist: coverage; extra == "coverage"
Requires-Dist: coveralls; extra == "coverage"
Provides-Extra: gurobi
Requires-Dist: gurobipy; extra == "gurobi"
Provides-Extra: highs
Requires-Dist: highspy; extra == "highs"
Dynamic: description
Dynamic: description-content-type
Dynamic: home-page
Dynamic: keywords
Dynamic: license
Dynamic: license-file
Dynamic: maintainer
Dynamic: maintainer-email
Dynamic: platform
Dynamic: project-url
Dynamic: provides-extra
Dynamic: requires-dist
Dynamic: summary
